test/Forecast_API.py
test/Weather_API.py
test/__init__.py
test/get_battery_percentage.py
BestSun-1.0.0.4.dist-info/METADATA
BestSun-1.0.0.4.dist-info/WHEEL
BestSun-1.0.0.4.dist-info/top_level.txt
BestSun-1.0.0.4.dist-info/RECORD
